foyou_down/__init__.py
foyou_down-0.0.7.dist-info/LICENSE
foyou_down-0.0.7.dist-info/METADATA
foyou_down-0.0.7.dist-info/WHEEL
foyou_down-0.0.7.dist-info/entry_points.txt
foyou_down-0.0.7.dist-info/top_level.txt
foyou_down-0.0.7.dist-info/RECORD
