Metadata-Version: 2.1
Name: foyou-down
Version: 0.0.7
Summary: python simple downloader
Home-page: https://github.com/foyoux/foyou-down
Author: foyou
Author-email: yimi.0822@qq.com
License: GPL-3.0
Project-URL: Source, https://github.com/foyoux/foyou-down
Project-URL: Bug Tracker, https://github.com/foyoux/foyou-down/issues
Keywords: downloader
Classifier: Programming Language :: Python :: 3
Classifier: Programming Language :: Python :: 3.7
Classifier: Programming Language :: Python :: 3.8
Classifier: Programming Language :: Python :: 3.9
Classifier: Programming Language :: Python :: 3.10
Classifier: Programming Language :: Python :: 3.11
Classifier: Programming Language :: Python :: 3.12
Classifier: License :: OSI Approved :: GNU General Public License v3 (GPLv3)
Classifier: Environment :: Console
Classifier: Natural Language :: Chinese (Simplified)
Classifier: Development Status :: 4 - Beta
Requires-Python: >=3.7
License-File: LICENSE
Requires-Dist: requests
Requires-Dist: coloredlogs
Requires-Dist: tqdm
